peewee_model_factory/__init__.py
peewee_model_factory/factory.py
tests/__init__.py
tests/conftest.py
tests/models.py
tests/test_fields.py
tests/utils.py
peewee_model_factory-0.1.1.dist-info/LICENSE
peewee_model_factory-0.1.1.dist-info/METADATA
peewee_model_factory-0.1.1.dist-info/WHEEL
peewee_model_factory-0.1.1.dist-info/top_level.txt
peewee_model_factory-0.1.1.dist-info/RECORD
