Metadata-Version: 2.1
Name: peewee-model-factory
Version: 0.1.1
Summary: A library to create peewee model instances for testing.
Home-page: https://github.com/kalombos/peewee-model-factory
Author: Nikolay Gorshkov
Author-email: nogamemorebrain@gmail.com
License: BSD
Keywords: python testing fixture generator peewee model factory peewee fixtures
Platform: UNKNOWN
Classifier: Development Status :: 3 - Alpha
Classifier: Intended Audience :: Developers
Classifier: Programming Language :: Python :: 3
Requires-Dist: peewee
Requires-Dist: pytz
